poetress/__init__.py
poetress/poetress.py
poetress/data/poetress_config.config
poetress-1.0.1.dist-info/LICENSE.md
poetress-1.0.1.dist-info/METADATA
poetress-1.0.1.dist-info/WHEEL
poetress-1.0.1.dist-info/entry_points.txt
poetress-1.0.1.dist-info/top_level.txt
poetress-1.0.1.dist-info/RECORD
